Workbook
Name Slicer_Region: #N/A

Sheet Sheet3
A1: SUMMARY OUTPUT
A3: Regression Statistics
A4: Multiple R | B4: 0.45808036
A5: R Square | B5: 0.20983762
A6: Adjusted R Square | B6: 0.20665148
A7: Standard Error | B7: 919.60715
A8: Observations | B8: 250
A10: ANOVA
B11: df | C11: SS | D11: MS | E11: F | F11: Significance F
A12: Regression | B12: 1 | C12: 55695917 | D12: 55695917 | E12: 65.859537 | F12: 2.2586479e-14
A13: Residual | B13: 248 | C13: 2.0972797e+08 | D13: 845677.32
A14: Total | B14: 249 | C14: 2.6542389e+08
B16: Coefficients | C16: Standard Error | D16: t Stat | E16: P-value | F16: Lower 95% | G16: Upper 95% | H16: Lower 95.0% | I16: Upper 95.0%
A17: Intercept | B17: -148.85465 | C17: 143.61334 | D17: -1.0364959 | E17: 0.3009804 | F17: -431.712 | G17: 134.0027 | H17: -431.712 | I17: 134.0027
A18: Quantity | B18: 353.793 | C18: 43.595323 | D18: 8.1153889 | E18: 2.2586479e-14 | F18: 267.92872 | G18: 439.65729 | H18: 267.92872 | I18: 439.65729

Sheet Sheet4
A3: Row Labels | B3: Sum of Unit_Price
A4: Appliances | B4: 399.94
A5: Electronics | B5: 6389.78
A6: Furniture | B6: 3399.86
A7: Grand Total | B7: 10189.58

Sheet Sheet2
A3: Row Labels | B3: Sum of Total_Amount
A4: Jan | B4: 4559.77
A5: Feb | B5: 5899.86
A6: Mar | B6: 449.95
A7: Apr | B7: 359.94
A8: May | B8: 1239.92
A9: Jun | B9: 5129.88
A10: Jul | B10: 8909.83
A11: Aug | B11: 1099.94
A12: Sep | B12: 3479.92
A13: Oct | B13: 449.97
A14: Nov | B14: 2629.87
A15: Dec | B15: 2189.9
A16: Grand Total | B16: 36398.75

Sheet Dashboard
D2: Sales Performance Dashboard
B4: Total Sale | D4: Total Quantity | F4: Total Customers | H4: Avg Order Value
B5: =GETPIVOTDATA("Sum of Total_Amount",Sheet5!$A$3) -> 36398.75 | D5: =SUM(GETPIVOTDATA("Sum of Quantity",Sheet5!$A$3)) -> 125 | F5: =SUM(GETPIVOTDATA("Count of Customer_ID",Sheet5!$A$3)) -> 42 | H5: =GETPIVOTDATA("Sum of Total_Amount",Sheet5!$A$3)/GETPIVOTDATA("Count of Transaction_ID",Sheet5!$A$3) -> 866.6369

Sheet Sheet5
A3: Row Labels | B3: Count of Transaction_ID | C3: Count of Customer_ID | D3: Sum of Quantity | E3: Sum of Total_Amount
A4: South | B4: 42 | C4: 42 | D4: 125 | E4: 36398.75
A5: Grand Total | B5: 42 | C5: 42 | D5: 125 | E5: 36398.75

Sheet Sheet1
A1: Transaction_ID | B1: Date | C1: Customer_ID | D1: Customer_Name | E1: Product_ID | F1: Product_Name | G1: Category | H1: Quantity | I1: Unit_Price | J1: Payment_Method | K1: Region | L1: Customer_Segment | M1: Customer_Since | N1: Total_Amount
A2: TRX0155 | B2: 45393 | C2: CUST023 | D2: Paul Baker | E2: P009 | F2: Monitor | G2: Electronics | H2: 3 | I2: 249.99 | J2: Cash | K2: Central | L2: Basic | M2: 44425 | N2: 749.97
A3: TRX0023 | B3: 45396 | C3: CUST013 | D3: Joseph Jackson | E3: P009 | F3: Monitor | G3: Electronics | H3: 3 | I3: 249.99 | J3: Credit Card | K3: Central | L3: Premium | M3: 44575 | N3: 749.97
A4: TRX0139 | B4: 45399 | C4: CUST021 | D4: Kevin Scott | E4: P005 | F4: Blender | G4: Appliances | H4: 3 | I4: 59.99 | J4: PayPal | K4: South | L4: Standard | M4: 45262 | N4: 179.97
A5: TRX0043 | B5: 45400 | C5: CUST046 | D5: Kathleen Bennett | E5: P005 | F5: Blender | G5: Appliances | H5: 3 | I5: 59.99 | J5: Cash | K5: North | L5: Premium | M5: 45114 | N5: 179.97
A6: TRX0212 | B6: 45400 | C6: CUST003 | D6: Michael Brown | E6: P008 | F6: Bookshelf | G6: Furniture | H6: 5 | I6: 149.99 | J6: Credit Card | K6: North | L6: Premium | M6: 45295 | N6: 749.95
A7: TRX0092 | B7: 45403 | C7: CUST024 | D7: Dorothy Nelson | E7: P005 | F7: Blender | G7: Appliances | H7: 2 | I7: 59.99 | J7: Cash | K7: West | L7: Standard | M7: 44746 | N7: 119.98
A8: TRX0193 | B8: 45403 | C8: CUST024 | D8: Dorothy Nelson | E8: P003 | F8: Headphones | G8: Electronics | H8: 5 | I8: 149.99 | J8: Credit Card | K8: Central | L8: Standard | M8: 44418 | N8: 749.95
A9: TRX0240 | B9: 45403 | C9: CUST017 | D9: Charles Allen | E9: P005 | F9: Blender | G9: Appliances | H9: 3 | I9: 59.99 | J9: Debit Card | K9: South | L9: Basic | M9: 45007 | N9: 179.97
A10: TRX0135 | B10: 45405 | C10: CUST009 | D10: Robert Thomas | E10: P001 | F10: Laptop | G10: Electronics | H10: 3 | I10: 899.99 | J10: PayPal | K10: East | L10: Standard | M10: 45299 | N10: 2699.97
A11: TRX0185 | B11: 45408 | C11: CUST026 | D11: Karen Hill | E11: P005 | F11: Blender | G11: Appliances | H11: 3 | I11: 59.99 | J11: Cash | K11: West | L11: Premium | M11: 45207 | N11: 179.97
A12: TRX0138 | B12: 45408 | C12: CUST022 | D12: Susan Green | E12: P008 | F12: Bookshelf | G12: Furniture | H12: 1 | I12: 149.99 | J12: Credit Card | K12: West | L12: Standard | M12: 45103 | N12: 149.99
A13: TRX0209 | B13: 45408 | C13: CUST046 | D13: Kathleen Bennett | E13: P008 | F13: Bookshelf | G13: Furniture | H13: 5 | I13: 149.99 | J13: Debit Card | K13: North | L13: Basic | M13: 44830 | N13: 749.95
... A251: TRX0064 | B251: 45758 | C251: CUST031 | D251: Steven Turner | E251: P010 | F251: Keyboard | G251: Electronics | H251: 3 | I251: 89.99 | J251: Debit Card | K251: North | L251: Premium | M251: 44878 | N251: 269.97

Sheet Sheet7
A1: Transaction_ID | B1: Date | C1: Customer_ID | D1: Customer_Name | E1: Product_ID | F1: Product_Name | G1: Category | H1: Quantity | I1: Unit_Price | J1: Payment_Method | K1: Region | L1: Customer_Segment | M1: Customer_Since | N1: Total_Amount | O1: NOW | P1: TODAY | Q1: Next month | R1: Customer tenure months | S1: Customer with highest sale | X1: Sort name | AD1: total high vale customers
A2: TRX0155 | B2: 45393 | C2: CUST023 | D2: Paul Baker | E2: P009 | F2: Monitor | G2: Electronics | H2: 3 | I2: 249.99 | J2: Cash | K2: Central | L2: Basic | M2: 44425 | N2: =I2*H2 -> 749.97 | O2: =NOW() -> 46324.651 | P2: =TODAY() -> 46324 | Q2: =TEXT(EOMONTH(M2,1),"mmmm") -> September | R2: =DATEDIF(M2,B2,"M") -> 31 | S2: {=_xlfn._xlws.FILTER(D2:D251,N2:N251=MAX(N2:N251))} -> Paul Baker | T2: {=COUNTIF(F2:F251,F2:F251)} -> 26 | U2: {=_xlfn.MODE.MULT(_xlfn.ANCHORARRAY(T2))} -> 26 | V2: =MATCH(U2,T2:T251,0) -> 1 | W2: {=INDEX(F2:F251,V2)} -> Monitor | X2: =LEFT(D2,1)&MID(D2,FIND(" ",D2)+1,1) -> PB | AA2: {=_xlfn.UNIQUE(D2:D251)} -> Paul Baker | AB2: =SUMIFS($N$2:$N$251,$D$2:$D$251,AA2) -> 8309.74 | AC2: =IF(AB2>5000,"high value","Regular") -> high value | AD2: =COUNTIF(AC2:AC51,AC2) -> 20 | AF2: =IF(I2=N2,I2,"no match") -> no match
A3: TRX0023 | B3: 45396 | C3: CUST013 | D3: Joseph Jackson | E3: P009 | F3: Monitor | G3: Electronics | H3: 3 | I3: 249.99 | J3: Credit Card | K3: Central | L3: Premium | M3: 44575 | N3: =I3*H3 -> 749.97 | O3: =NOW() -> 46324.651 | P3: =TODAY() -> 46324 | Q3: =TEXT(EOMONTH(M3,1),"mmmm") -> February | R3: =DATEDIF(M3,B3,"M") -> 27 | S3: Edward Mitchell | T3: 26 | X3: =LEFT(D3,1)&MID(D3,FIND(" ",D3)+1,1) -> JJ | AA3: Joseph Jackson | AB3: =SUMIFS($N$2:$N$251,$D$2:$D$251,AA3) -> 6949.84 | AC3: =IF(AB3>5000,"high value","Regular") -> high value | AF3: =IF(I3=N3,I3,"no match") -> no match
A4: TRX0139 | B4: 45399 | C4: CUST021 | D4: Kevin Scott | E4: P005 | F4: Blender | G4: Appliances | H4: 3 | I4: 59.99 | J4: PayPal | K4: South | L4: Standard | M4: 45262 | N4: =I4*H4 -> 179.97 | O4: =NOW() -> 46324.651 | P4: =TODAY() -> 46324 | Q4: =TEXT(EOMONTH(M4,1),"mmmm") -> January | R4: =DATEDIF(M4,B4,"M") -> 4 | S4: Joseph Jackson | T4: 29 | X4: =LEFT(D4,1)&MID(D4,FIND(" ",D4)+1,1) -> KS | AA4: Kevin Scott | AB4: =SUMIFS($N$2:$N$251,$D$2:$D$251,AA4) -> 3259.87 | AC4: =IF(AB4>5000,"high value","Regular") -> Regular | AF4: =IF(I4=N4,I4,"no match") -> no match
A5: TRX0043 | B5: 45400 | C5: CUST046 | D5: Kathleen Bennett | E5: P005 | F5: Blender | G5: Appliances | H5: 3 | I5: 59.99 | J5: Cash | K5: North | L5: Premium | M5: 45114 | N5: =I5*H5 -> 179.97 | O5: =NOW() -> 46324.651 | P5: =TODAY() -> 46324 | Q5: =TEXT(EOMONTH(M5,1),"mmmm") -> August | R5: =DATEDIF(M5,B5,"M") -> 9 | S5: Gerald Murphy | T5: 29 | X5: =LEFT(D5,1)&MID(D5,FIND(" ",D5)+1,1) -> KB | AA5: Kathleen Bennett | AB5: =SUMIFS($N$2:$N$251,$D$2:$D$251,AA5) -> 4309.81 | AC5: =IF(AB5>5000,"high value","Regular") -> Regular | AF5: =IF(I5=N5,I5,"no match") -> no match
A6: TRX0212 | B6: 45400 | C6: CUST003 | D6: Michael Brown | E6: P008 | F6: Bookshelf | G6: Furniture | H6: 5 | I6: 149.99 | J6: Credit Card | K6: North | L6: Premium | M6: 45295 | N6: =I6*H6 -> 749.95 | O6: =NOW() -> 46324.651 | P6: =TODAY() -> 46324 | Q6: =TEXT(EOMONTH(M6,1),"mmmm") -> February | R6: =DATEDIF(M6,B6,"M") -> 3 | S6: Daniel King | T6: 35 | X6: =LEFT(D6,1)&MID(D6,FIND(" ",D6)+1,1) -> MB | AA6: Michael Brown | AB6: =SUMIFS($N$2:$N$251,$D$2:$D$251,AA6) -> 6169.74 | AC6: =IF(AB6>5000,"high value","Regular") -> high value | AF6: =IF(I6=N6,I6,"no match") -> no match
A7: TRX0092 | B7: 45403 | C7: CUST024 | D7: Dorothy Nelson | E7: P005 | F7: Blender | G7: Appliances | H7: 2 | I7: 59.99 | J7: Cash | K7: West | L7: Standard | M7: 44746 | N7: =I7*H7 -> 119.98 | O7: =NOW() -> 46324.651 | P7: =TODAY() -> 46324 | Q7: =TEXT(EOMONTH(M7,1),"mmmm") -> August | R7: =DATEDIF(M7,B7,"M") -> 21 | S7: Harry Morgan | T7: 29 | X7: =LEFT(D7,1)&MID(D7,FIND(" ",D7)+1,1) -> DN | AA7: Dorothy Nelson | AB7: =SUMIFS($N$2:$N$251,$D$2:$D$251,AA7) -> 8269.79 | AC7: =IF(AB7>5000,"high value","Regular") -> high value | AF7: =IF(I7=N7,I7,"no match") -> no match
A8: TRX0193 | B8: 45403 | C8: CUST024 | D8: Dorothy Nelson | E8: P003 | F8: Headphones | G8: Electronics | H8: 5 | I8: 149.99 | J8: Credit Card | K8: Central | L8: Standard | M8: 44418 | N8: =I8*H8 -> 749.95 | O8: =NOW() -> 46324.651 | P8: =TODAY() -> 46324 | Q8: =TEXT(EOMONTH(M8,1),"mmmm") -> September | R8: =DATEDIF(M8,B8,"M") -> 32 | T8: 16 | X8: =LEFT(D8,1)&MID(D8,FIND(" ",D8)+1,1) -> DN | AA8: Charles Allen | AB8: =SUMIFS($N$2:$N$251,$D$2:$D$251,AA8) -> 5089.73 | AC8: =IF(AB8>5000,"high value","Regular") -> high value | AF8: =IF(I8=N8,I8,"no match") -> no match
A9: TRX0240 | B9: 45403 | C9: CUST017 | D9: Charles Allen | E9: P005 | F9: Blender | G9: Appliances | H9: 3 | I9: 59.99 | J9: Debit Card | K9: South | L9: Basic | M9: 45007 | N9: =I9*H9 -> 179.97 | O9: =NOW() -> 46324.651 | P9: =TODAY() -> 46324 | Q9: =TEXT(EOMONTH(M9,1),"mmmm") -> April | R9: =DATEDIF(M9,B9,"M") -> 12 | T9: 29 | X9: =LEFT(D9,1)&MID(D9,FIND(" ",D9)+1,1) -> CA | AA9: Robert Thomas | AB9: =SUMIFS($N$2:$N$251,$D$2:$D$251,AA9) -> 3509.9 | AC9: =IF(AB9>5000,"high value","Regular") -> Regular | AF9: =IF(I9=N9,I9,"no match") -> no match
A10: TRX0135 | B10: 45405 | C10: CUST009 | D10: Robert Thomas | E10: P001 | F10: Laptop | G10: Electronics | H10: 3 | I10: 899.99 | J10: PayPal | K10: East | L10: Standard | M10: 45299 | N10: =I10*H10 -> 2699.97 | O10: =NOW() -> 46324.651 | P10: =TODAY() -> 46324 | Q10: =TEXT(EOMONTH(M10,1),"mmmm") -> February | R10: =DATEDIF(M10,B10,"M") -> 3 | T10: 24 | X10: =LEFT(D10,1)&MID(D10,FIND(" ",D10)+1,1) -> RT | AA10: Karen Hill | AB10: =SUMIFS($N$2:$N$251,$D$2:$D$251,AA10) -> 8009.77 | AC10: =IF(AB10>5000,"high value","Regular") -> high value | AF10: =IF(I10=N10,I10,"no match") -> no match
A11: TRX0185 | B11: 45408 | C11: CUST026 | D11: Karen Hill | E11: P005 | F11: Blender | G11: Appliances | H11: 3 | I11: 59.99 | J11: Cash | K11: West | L11: Premium | M11: 45207 | N11: =I11*H11 -> 179.97 | O11: =NOW() -> 46324.651 | P11: =TODAY() -> 46324 | Q11: =TEXT(EOMONTH(M11,1),"mmmm") -> November | R11: =DATEDIF(M11,B11,"M") -> 6 | T11: 29 | X11: =LEFT(D11,1)&MID(D11,FIND(" ",D11)+1,1) -> KH | AA11: Susan Green | AB11: =SUMIFS($N$2:$N$251,$D$2:$D$251,AA11) -> 1979.89 | AC11: =IF(AB11>5000,"high value","Regular") -> Regular | AF11: =IF(I11=N11,I11,"no match") -> no match
A12: TRX0138 | B12: 45408 | C12: CUST022 | D12: Susan Green | E12: P008 | F12: Bookshelf | G12: Furniture | H12: 1 | I12: 149.99 | J12: Credit Card | K12: West | L12: Standard | M12: 45103 | N12: =I12*H12 -> 149.99 | O12: =NOW() -> 46324.651 | P12: =TODAY() -> 46324 | Q12: =TEXT(EOMONTH(M12,1),"mmmm") -> July | R12: =DATEDIF(M12,B12,"M") -> 10 | T12: 35 | X12: =LEFT(D12,1)&MID(D12,FIND(" ",D12)+1,1) -> SG | AA12: Peter Richardson | AB12: =SUMIFS($N$2:$N$251,$D$2:$D$251,AA12) -> 5949.85 | AC12: =IF(AB12>5000,"high value","Regular") -> high value | AF12: =IF(I12=N12,I12,"no match") -> 149.99
A13: TRX0209 | B13: 45408 | C13: CUST046 | D13: Kathleen Bennett | E13: P008 | F13: Bookshelf | G13: Furniture | H13: 5 | I13: 149.99 | J13: Debit Card | K13: North | L13: Basic | M13: 44830 | N13: =I13*H13 -> 749.95 | O13: =NOW() -> 46324.651 | P13: =TODAY() -> 46324 | Q13: =TEXT(EOMONTH(M13,1),"mmmm") -> October | R13: =DATEDIF(M13,B13,"M") -> 19 | T13: 35 | X13: =LEFT(D13,1)&MID(D13,FIND(" ",D13)+1,1) -> KB | AA13: Dennis Gray | AB13: =SUMIFS($N$2:$N$251,$D$2:$D$251,AA13) -> 479.92 | AC13: =IF(AB13>5000,"high value","Regular") -> Regular | AF13: =IF(I13=N13,I13,"no match") -> no match
A14: TRX0246 | B14: 45408 | C14: CUST041 | D14: Peter Richardson | E14: P008 | F14: Bookshelf | G14: Furniture | H14: 3 | I14: 149.99 | J14: Cash | K14: North | L14: Premium | M14: 44806 | N14: =I14*H14 -> 449.97 | O14: =NOW() -> 46324.651 | P14: =TODAY() -> 46324 | Q14: =TEXT(EOMONTH(M14,1),"mmmm") -> October | R14: =DATEDIF(M14,B14,"M") -> 19 | T14: 35 | X14: =LEFT(D14,1)&MID(D14,FIND(" ",D14)+1,1) -> PR | AA14: Michelle Rogers | AB14: =SUMIFS($N$2:$N$251,$D$2:$D$251,AA14) -> 4199.94 | AC14: =IF(AB14>5000,"high value","Regular") -> Regular | AF14: =IF(I14=N14,I14,"no match") -> no match
A15: TRX0067 | B15: 45409 | C15: CUST043 | D15: Dennis Gray | E15: P005 | F15: Blender | G15: Appliances | H15: 3 | I15: 59.99 | J15: Credit Card | K15: North | L15: Standard | M15: 45351 | N15: =I15*H15 -> 179.97 | O15: =NOW() -> 46324.651 | P15: =TODAY() -> 46324 | Q15: =TEXT(EOMONTH(M15,1),"mmmm") -> March | R15: =DATEDIF(M15,B15,"M") -> 1 | T15: 29 | X15: =LEFT(D15,1)&MID(D15,FIND(" ",D15)+1,1) -> DG | AA15: George Adams | AB15: =SUMIFS($N$2:$N$251,$D$2:$D$251,AA15) -> 3779.93 | AC15: =IF(AB15>5000,"high value","Regular") -> Regular | AF15: =IF(I15=N15,I15,"no match") -> no match
A16: TRX0191 | B16: 45409 | C16: CUST038 | D16: Michelle Rogers | E16: P002 | F16: Smartphone | G16: Electronics | H16: 3 | I16: 699.99 | J16: Credit Card | K16: West | L16: Basic | M16: 44577 | N16: =I16*H16 -> 2099.97 | O16: =NOW() -> 46324.651 | P16: =TODAY() -> 46324 | Q16: =TEXT(EOMONTH(M16,1),"mmmm") -> February | R16: =DATEDIF(M16,B16,"M") -> 27 | T16: 31 | X16: =LEFT(D16,1)&MID(D16,FIND(" ",D16)+1,1) -> MR | AA16: Mark Carter | AB16: =SUMIFS($N$2:$N$251,$D$2:$D$251,AA16) -> 15659.65 | AC16: =IF(AB16>5000,"high value","Regular") -> high value | AF16: =IF(I16=N16,I16,"no match") -> no match
A17: TRX0230 | B17: 45409 | C17: CUST027 | D17: George Adams | E17: P001 | F17: Laptop | G17: Electronics | H17: 1 | I17: 899.99 | J17: Debit Card | K17: North | L17: Standard | M17: 44920 | N17: =I17*H17 -> 899.99 | O17: =NOW() -> 46324.651 | P17: =TODAY() -> 46324 | Q17: =TEXT(EOMONTH(M17,1),"mmmm") -> January | R17: =DATEDIF(M17,B17,"M") -> 16 | T17: 24 | X17: =LEFT(D17,1)&MID(D17,FIND(" ",D17)+1,1) -> GA | AA17: Maria Garcia | AB17: =SUMIFS($N$2:$N$251,$D$2:$D$251,AA17) -> 1909.93 | AC17: =IF(AB17>5000,"high value","Regular") -> Regular | AF17: =IF(I17=N17,I17,"no match") -> 899.99
A18: TRX0049 | B18: 45410 | C18: CUST025 | D18: Mark Carter | E18: P008 | F18: Bookshelf | G18: Furniture | H18: 4 | I18: 149.99 | J18: Debit Card | K18: North | L18: Premium | M18: 45374 | N18: =I18*H18 -> 599.96 | O18: =NOW() -> 46324.651 | P18: =TODAY() -> 46324 | Q18: =TEXT(EOMONTH(M18,1),"mmmm") -> April | R18: =DATEDIF(M18,B18,"M") -> 1 | T18: 35 | X18: =LEFT(D18,1)&MID(D18,FIND(" ",D18)+1,1) -> MC | AA18: Virginia Sanders | AB18: =SUMIFS($N$2:$N$251,$D$2:$D$251,AA18) -> 4789.79 | AC18: =IF(AB18>5000,"high value","Regular") -> Regular | AF18: =IF(I18=N18,I18,"no match") -> no match
A19: TRX0134 | B19: 45410 | C19: CUST010 | D19: Maria Garcia | E19: P002 | F19: Smartphone | G19: Electronics | H19: 2 | I19: 699.99 | J19: Cash | K19: North | L19: Basic | M19: 44781 | N19: =I19*H19 -> 1399.98 | O19: =NOW() -> 46324.651 | P19: =TODAY() -> 46324 | Q19: =TEXT(EOMONTH(M19,1),"mmmm") -> September | R19: =DATEDIF(M19,B19,"M") -> 20 | T19: 31 | X19: =LEFT(D19,1)&MID(D19,FIND(" ",D19)+1,1) -> MG | AA19: Barbara Young | AB19: =SUMIFS($N$2:$N$251,$D$2:$D$251,AA19) -> 10649.8 | AC19: =IF(AB19>5000,"high value","Regular") -> high value | AF19: =IF(I19=N19,I19,"no match") -> no match
... A51: TRX0154 | B51: 45459 | C51: CUST023 | D51: Paul Baker | E51: P001 | F51: Laptop | G51: Electronics | H51: 5 | I51: 899.99 | J51: Credit Card | K51: South | L51: Standard | M51: 44974 | N51: =I51*H51 -> 4499.95 | O51: =NOW() -> 46324.651 | P51: =TODAY() -> 46324 | Q51: =TEXT(EOMONTH(M51,1),"mmmm") -> March | R51: =DATEDIF(M51,B51,"M") -> 15 | T51: 24 | X51: =LEFT(D51,1)&MID(D51,FIND(" ",D51)+1,1) -> PB | AA51: John Smith | AB51: =SUMIFS($N$2:$N$251,$D$2:$D$251,AA51) -> 599.96 | AC51: =IF(AB51>5000,"high value","Regular") -> Regular | AF51: =IF(I51=N51,I51,"no match") -> no match
A52: TRX0044 | B52: 45459 | C52: CUST029 | D52: Edward Mitchell | E52: P001 | F52: Laptop | G52: Electronics | H52: 5 | I52: 899.99 | J52: PayPal | K52: East | L52: Premium | M52: 45278 | N52: =I52*H52 -> 4499.95 | O52: =NOW() -> 46324.651 | P52: =TODAY() -> 46324 | Q52: =TEXT(EOMONTH(M52,1),"mmmm") -> January | R52: =DATEDIF(M52,B52,"M") -> 5 | T52: 24 | X52: =LEFT(D52,1)&MID(D52,FIND(" ",D52)+1,1) -> EM | AF52: =IF(I52=N52,I52,"no match") -> no match
A53: TRX0061 | B53: 45460 | C53: CUST028 | D53: Betty Campbell | E53: P005 | F53: Blender | G53: Appliances | H53: 1 | I53: 59.99 | J53: Debit Card | K53: West | L53: Premium | M53: 45190 | N53: =I53*H53 -> 59.99 | O53: =NOW() -> 46324.651 | P53: =TODAY() -> 46324 | Q53: =TEXT(EOMONTH(M53,1),"mmmm") -> October | R53: =DATEDIF(M53,B53,"M") -> 8 | T53: 29 | X53: =LEFT(D53,1)&MID(D53,FIND(" ",D53)+1,1) -> BC | AF53: =IF(I53=N53,I53,"no match") -> 59.99
A54: TRX0150 | B54: 45460 | C54: CUST008 | D54: Jennifer Taylor | E54: P007 | F54: Desk | G54: Furniture | H54: 2 | I54: 299.99 | J54: Debit Card | K54: East | L54: Standard | M54: 45253 | N54: =I54*H54 -> 599.98 | O54: =NOW() -> 46324.651 | P54: =TODAY() -> 46324 | Q54: =TEXT(EOMONTH(M54,1),"mmmm") -> December | R54: =DATEDIF(M54,B54,"M") -> 6 | T54: 26 | X54: =LEFT(D54,1)&MID(D54,FIND(" ",D54)+1,1) -> JT | AF54: =IF(I54=N54,I54,"no match") -> no match
A55: TRX0025 | B55: 45468 | C55: CUST049 | D55: Raymond Ross | E55: P010 | F55: Keyboard | G55: Electronics | H55: 4 | I55: 89.99 | J55: Debit Card | K55: South | L55: Basic | M55: 45281 | N55: =I55*H55 -> 359.96 | O55: =NOW() -> 46324.651 | P55: =TODAY() -> 46324 | Q55: =TEXT(EOMONTH(M55,1),"mmmm") -> January | R55: =DATEDIF(M55,B55,"M") -> 6 | T55: 34 | X55: =LEFT(D55,1)&MID(D55,FIND(" ",D55)+1,1) -> RR | AF55: =IF(I55=N55,I55,"no match") -> no match
A56: TRX0078 | B56: 45469 | C56: CUST021 | D56: Kevin Scott | E56: P004 | F56: Coffee Maker | G56: Appliances | H56: 1 | I56: 79.99 | J56: PayPal | K56: Central | L56: Premium | M56: 45352 | N56: =I56*H56 -> 79.99 | O56: =NOW() -> 46324.651 | P56: =TODAY() -> 46324 | Q56: =TEXT(EOMONTH(M56,1),"mmmm") -> April | R56: =DATEDIF(M56,B56,"M") -> 3 | T56: 14 | X56: =LEFT(D56,1)&MID(D56,FIND(" ",D56)+1,1) -> KS | AF56: =IF(I56=N56,I56,"no match") -> 79.99
A57: TRX0007 | B57: 45469 | C57: CUST009 | D57: Robert Thomas | E57: P010 | F57: Keyboard | G57: Electronics | H57: 2 | I57: 89.99 | J57: Cash | K57: West | L57: Basic | M57: 44438 | N57: =I57*H57 -> 179.98 | O57: =NOW() -> 46324.651 | P57: =TODAY() -> 46324 | Q57: =TEXT(EOMONTH(M57,1),"mmmm") -> September | R57: =DATEDIF(M57,B57,"M") -> 33 | T57: 34 | X57: =LEFT(D57,1)&MID(D57,FIND(" ",D57)+1,1) -> RT | AF57: =IF(I57=N57,I57,"no match") -> no match
A58: TRX0184 | B58: 45471 | C58: CUST046 | D58: Kathleen Bennett | E58: P002 | F58: Smartphone | G58: Electronics | H58: 3 | I58: 699.99 | J58: Credit Card | K58: East | L58: Premium | M58: 45102 | N58: =I58*H58 -> 2099.97 | O58: =NOW() -> 46324.651 | P58: =TODAY() -> 46324 | Q58: =TEXT(EOMONTH(M58,1),"mmmm") -> July | R58: =DATEDIF(M58,B58,"M") -> 12 | T58: 31 | X58: =LEFT(D58,1)&MID(D58,FIND(" ",D58)+1,1) -> KB | AF58: =IF(I58=N58,I58,"no match") -> no match
A59: TRX0104 | B59: 45471 | C59: CUST012 | D59: Patricia Moore | E59: P001 | F59: Laptop | G59: Electronics | H59: 4 | I59: 899.99 | J59: Credit Card | K59: East | L59: Premium | M59: 44993 | N59: =I59*H59 -> 3599.96 | O59: =NOW() -> 46324.651 | P59: =TODAY() -> 46324 | Q59: =TEXT(EOMONTH(M59,1),"mmmm") -> April | R59: =DATEDIF(M59,B59,"M") -> 15 | T59: 24 | X59: =LEFT(D59,1)&MID(D59,FIND(" ",D59)+1,1) -> PM | AF59: =IF(I59=N59,I59,"no match") -> no match
A60: TRX0127 | B60: 45472 | C60: CUST030 | D60: Helen Roberts | E60: P008 | F60: Bookshelf | G60: Furniture | H60: 1 | I60: 149.99 | J60: PayPal | K60: East | L60: Basic | M60: 44851 | N60: =I60*H60 -> 149.99 | O60: =NOW() -> 46324.651 | P60: =TODAY() -> 46324 | Q60: =TEXT(EOMONTH(M60,1),"mmmm") -> November | R60: =DATEDIF(M60,B60,"M") -> 20 | T60: 35 | X60: =LEFT(D60,1)&MID(D60,FIND(" ",D60)+1,1) -> HR | AF60: =IF(I60=N60,I60,"no match") -> 149.99
A61: TRX0096 | B61: 45474 | C61: CUST002 | D61: Emma Wilson | E61: P010 | F61: Keyboard | G61: Electronics | H61: 2 | I61: 89.99 | J61: PayPal | K61: Central | L61: Premium | M61: 45275 | N61: =I61*H61 -> 179.98 | O61: =NOW() -> 46324.651 | P61: =TODAY() -> 46324 | Q61: =TEXT(EOMONTH(M61,1),"mmmm") -> January | R61: =DATEDIF(M61,B61,"M") -> 6 | T61: 34 | X61: =LEFT(D61,1)&MID(D61,FIND(" ",D61)+1,1) -> EW | AF61: =IF(I61=N61,I61,"no match") -> no match
A62: TRX0192 | B62: 45475 | C62: CUST017 | D62: Charles Allen | E62: P010 | F62: Keyboard | G62: Electronics | H62: 1 | I62: 89.99 | J62: PayPal | K62: West | L62: Standard | M62: 44802 | N62: =I62*H62 -> 89.99 | O62: =NOW() -> 46324.651 | P62: =TODAY() -> 46324 | Q62: =TEXT(EOMONTH(M62,1),"mmmm") -> September | R62: =DATEDIF(M62,B62,"M") -> 22 | T62: 34 | X62: =LEFT(D62,1)&MID(D62,FIND(" ",D62)+1,1) -> CA | AF62: =IF(I62=N62,I62,"no match") -> 89.99
A63: TRX0052 | B63: 45476 | C63: CUST022 | D63: Susan Green | E63: P010 | F63: Keyboard | G63: Electronics | H63: 1 | I63: 89.99 | J63: Cash | K63: South | L63: Standard | M63: 44611 | N63: =I63*H63 -> 89.99 | O63: =NOW() -> 46324.651 | P63: =TODAY() -> 46324 | Q63: =TEXT(EOMONTH(M63,1),"mmmm") -> March | R63: =DATEDIF(M63,B63,"M") -> 28 | T63: 34 | X63: =LEFT(D63,1)&MID(D63,FIND(" ",D63)+1,1) -> SG | AF63: =IF(I63=N63,I63,"no match") -> 89.99
... A251: TRX0064 | B251: 45758 | C251: CUST031 | D251: Steven Turner | E251: P010 | F251: Keyboard | G251: Electronics | H251: 3 | I251: 89.99 | J251: Debit Card | K251: North | L251: Premium | M251: 44878 | N251: =I251*H251 -> 269.97 | O251: =NOW() -> 46324.651 | P251: =TODAY() -> 46324 | Q251: =TEXT(EOMONTH(M251,1),"mmmm") -> December | R251: =DATEDIF(M251,B251,"M") -> 28 | T251: 34 | X251: =LEFT(D251,1)&MID(D251,FIND(" ",D251)+1,1) -> ST | AF251: =IF(I251=N251,I251,"no match") -> no match

Sheet premium
A1: premium customer
A3: Customer_Name | B3: Product_ID | C3: Product_Name | D3: Category | E3: Quantity | F3: Unit_Price | G3: Payment_Method | H3: Region | I3: Customer_Segment | J3: Customer_Since | K3: Total_Amount
A4: {=_xlfn._xlws.FILTER(Sheet7!D2:N251,Sheet7!L2:L251="Premium","not a premiun")} -> Joseph Jackson | B4: P009 | C4: Monitor | D4: Electronics | E4: 3 | F4: 249.99 | G4: Credit Card | H4: Central | I4: Premium | J4: 44575 | K4: 749.97
A5: Kathleen Bennett | B5: P005 | C5: Blender | D5: Appliances | E5: 3 | F5: 59.99 | G5: Cash | H5: North | I5: Premium | J5: 45114 | K5: 179.97
A6: Michael Brown | B6: P008 | C6: Bookshelf | D6: Furniture | E6: 5 | F6: 149.99 | G6: Credit Card | H6: North | I6: Premium | J6: 45295 | K6: 749.95
A7: Karen Hill | B7: P005 | C7: Blender | D7: Appliances | E7: 3 | F7: 59.99 | G7: Cash | H7: West | I7: Premium | J7: 45207 | K7: 179.97
A8: Peter Richardson | B8: P008 | C8: Bookshelf | D8: Furniture | E8: 3 | F8: 149.99 | G8: Cash | H8: North | I8: Premium | J8: 44806 | K8: 449.97
A9: Mark Carter | B9: P008 | C9: Bookshelf | D9: Furniture | E9: 4 | F9: 149.99 | G9: Debit Card | H9: North | I9: Premium | J9: 45374 | K9: 599.96
A10: Virginia Sanders | B10: P009 | C10: Monitor | D10: Electronics | E10: 3 | F10: 249.99 | G10: Credit Card | H10: North | I10: Premium | J10: 45224 | K10: 749.97
A11: Mark Carter | B11: P007 | C11: Desk | D11: Furniture | E11: 4 | F11: 299.99 | G11: Cash | H11: West | I11: Premium | J11: 44716 | K11: 1199.96
A12: Linda Martin | B12: P004 | C12: Coffee Maker | D12: Appliances | E12: 3 | F12: 79.99 | G12: PayPal | H12: East | I12: Premium | J12: 45012 | K12: 239.97
A13: Patricia Moore | B13: P010 | C13: Keyboard | D13: Electronics | E13: 5 | F13: 89.99 | G13: Cash | H13: North | I13: Premium | J13: 44919 | K13: 449.95
A14: Emma Wilson | B14: P008 | C14: Bookshelf | D14: Furniture | E14: 3 | F14: 149.99 | G14: Credit Card | H14: West | I14: Premium | J14: 45068 | K14: 449.97
A15: Kevin Scott | B15: P001 | C15: Laptop | D15: Electronics | E15: 1 | F15: 899.99 | G15: Credit Card | H15: West | I15: Premium | J15: 44578 | K15: 899.99
A16: Steven Turner | B16: P006 | C16: Office Chair | D16: Furniture | E16: 3 | F16: 199.99 | G16: Credit Card | H16: North | I16: Premium | J16: 45292 | K16: 599.97
... A98: Steven Turner | B98: P010 | C98: Keyboard | D98: Electronics | E98: 3 | F98: 89.99 | G98: Debit Card | H98: North | I98: Premium | J98: 44878 | K98: 269.97

Sheet Sheet6
A1: Customer_Name | B1: Product_ID | C1: Product_Name | D1: Category | E1: Quantity | F1: Unit_Price | G1: Payment_Method | H1: Region | I1: Customer_Segment | J1: Customer_Since | K1: Total_Amount
A2: Paul Baker | B2: P009 | C2: Monitor | D2: Electronics | E2: 4 | F2: 249.99 | G2: Cash | H2: Central | I2: Basic | J2: 44425 | K2: =F2*E2 -> 999.96
A3: Joseph Jackson | B3: P009 | C3: Monitor | D3: Electronics | E3: 3 | F3: 249.99 | G3: Credit Card | H3: Central | I3: Premium | J3: 44575 | K3: =F3*E3 -> 749.97
A4: Kevin Scott | B4: P005 | C4: Blender | D4: Appliances | E4: 2 | F4: 59.99 | G4: PayPal | H4: South | I4: Standard | J4: 45262 | K4: =F4*E4 -> 119.98
A5: Kathleen Bennett | B5: P005 | C5: Blender | D5: Appliances | E5: 4 | F5: 59.99 | G5: Cash | H5: North | I5: Premium | J5: 45114 | K5: =F5*E5 -> 239.96
A6: Michael Brown | B6: P008 | C6: Bookshelf | D6: Furniture | E6: 3 | F6: 149.99 | G6: Credit Card | H6: North | I6: Premium | J6: 45295 | K6: =F6*E6 -> 449.97
A7: Dorothy Nelson | B7: P005 | C7: Blender | D7: Appliances | E7: 2 | F7: 59.99 | G7: Cash | H7: West | I7: Standard | J7: 44746 | K7: =F7*E7 -> 119.98
A8: Dorothy Nelson | B8: P003 | C8: Headphones | D8: Electronics | E8: 5 | F8: 149.99 | G8: Credit Card | H8: Central | I8: Standard | J8: 44418 | K8: =F8*E8 -> 749.95
A9: Charles Allen | B9: P005 | C9: Blender | D9: Appliances | E9: 3 | F9: 59.99 | G9: Debit Card | H9: South | I9: Basic | J9: 45007 | K9: =F9*E9 -> 179.97
A10: Robert Thomas | B10: P001 | C10: Laptop | D10: Electronics | E10: 3 | F10: 899.99 | G10: PayPal | H10: East | I10: Standard | J10: 45299 | K10: =F10*E10 -> 2699.97
A11: Karen Hill | B11: P005 | C11: Blender | D11: Appliances | E11: 3 | F11: 59.99 | G11: Cash | H11: West | I11: Premium | J11: 45207 | K11: =F11*E11 -> 179.97
A12: Susan Green | B12: P008 | C12: Bookshelf | D12: Furniture | E12: 1 | F12: 149.99 | G12: Credit Card | H12: West | I12: Standard | J12: 45103 | K12: =F12*E12 -> 149.99
A13: Kathleen Bennett | B13: P008 | C13: Bookshelf | D13: Furniture | E13: 5 | F13: 160 | G13: Debit Card | H13: North | I13: Basic | J13: 44830 | K13: =F13*E13 -> 800
... A251: Steven Turner | B251: P010 | C251: Keyboard | D251: Electronics | E251: 3 | F251: 89.99 | G251: Debit Card | H251: North | I251: Premium | J251: 44878 | K251: =F251*E251 -> 269.97

Sheet Sheet9
A3: Row Labels | B3: Sum of Total_Amount
A4: Blender | B4: 779.87
A5: Bookshelf | B5: 1349.91
A6: Coffee Maker | B6: 319.96
A7: Desk | B7: 6599.78
A8: Headphones | B8: 899.94
A9: Keyboard | B9: 2249.75
A10: Laptop | B10: 12599.86
A11: Monitor | B11: 3499.86
A12: Office Chair | B12: 1799.91
A13: Smartphone | B13: 6299.91
A14: Grand Total | B14: 36398.75
